[
  {
    "search_term": "dey.chandan1979@gmail.com",
    "timestamp": "2025-02-07 00:29:38",
    "results": [
      "Invite Friends\nNot seeing your friends here? Send them an invite to join Skype!"
    ]
  },
  {
    "search_term": "accounts.delhi@infodriveindia.com",
    "timestamp": "2025-02-07 00:29:45",
    "results": [
      "Invite Friends\nNot seeing your friends here? Send them an invite to join Skype!"
    ]
  },
  {
    "search_term": "oail@oceanagro.com",
    "timestamp": "2025-02-07 00:29:52",
    "results": [
      "Invite Friends\nNot seeing your friends here? Send them an invite to join Skype!"
    ]
  },
  {
    "search_term": "bkkp12@gmail.com",
    "timestamp": "2025-02-07 00:29:59",
    "results": [
      "Invite Friends\nNot seeing your friends here? Send them an invite to join Skype!"
    ]
  },
  {
    "search_term": "dppl_6819@yahoo.co.in",
    "timestamp": "2025-02-07 00:30:07",
    "results": [
      "Invite Friends\nNot seeing your friends here? Send them an invite to join Skype!"
    ]
  },
  {
    "search_term": "gen.admin@boyestumi.in",
    "timestamp": "2025-02-07 00:30:14",
    "results": [
      "Invite Friends\nNot seeing your friends here? Send them an invite to join Skype!"
    ]
  },
  {
    "search_term": "vintechpoly@gmail.com",
    "timestamp": "2025-02-07 00:30:21",
    "results": [
      "Invite Friends\nNot seeing your friends here? Send them an invite to join Skype!"
    ]
  },
  {
    "search_term": "sanabinay@gmail.com",
    "timestamp": "2025-02-07 00:30:28",
    "results": [
      "Invite Friends\nNot seeing your friends here? Send them an invite to join Skype!"
    ]
  },
  {
    "search_term": "himanshu.srivastava@thebirdgroup.com",
    "timestamp": "2025-02-07 00:30:35",
    "results": [
      "Invite Friends\nNot seeing your friends here? Send them an invite to join Skype!"
    ]
  },
  {
    "search_term": "dhiraj@tatanykshipping.com",
    "timestamp": "2025-02-07 00:30:43",
    "results": [
      "Invite Friends\nNot seeing your friends here? Send them an invite to join Skype!"
    ]
  },
  {
    "search_term": "rathincdel@yahoo.co.in",
    "timestamp": "2025-02-07 00:30:50",
    "results": [
      "Invite Friends\nNot seeing your friends here? Send them an invite to join Skype!"
    ]
  },
  {
    "search_term": "theunitedengg@gmail.com",
    "timestamp": "2025-02-07 00:30:57",
    "results": [
      "Invite Friends\nNot seeing your friends here? Send them an invite to join Skype!"
    ]
  },
  {
    "search_term": "Manish.Singh@fonterrafuture.in",
    "timestamp": "2025-02-07 00:31:04",
    "results": [
      "Invite Friends\nNot seeing your friends here? Send them an invite to join Skype!"
    ]
  },
  {
    "search_term": "anuresh.chauhan@gmail.com",
    "timestamp": "2025-02-07 00:31:11",
    "results": [
      "Invite Friends\nNot seeing your friends here? Send them an invite to join Skype!"
    ]
  },
  {
    "search_term": "accts@fortunerealty.in",
    "timestamp": "2025-02-07 00:31:19",
    "results": [
      "Invite Friends\nNot seeing your friends here? Send them an invite to join Skype!"
    ]
  },
  {
    "search_term": "bandyos@asgbiochem.com",
    "timestamp": "2025-02-07 00:31:26",
    "results": [
      "Invite Friends\nNot seeing your friends here? Send them an invite to join Skype!"
    ]
  },
  {
    "search_term": "ca.pawan@gmail.com",
    "timestamp": "2025-02-07 00:31:33",
    "results": [
      "Invite Friends\nNot seeing your friends here? Send them an invite to join Skype!"
    ]
  },
  {
    "search_term": "tarakgst.arka@gmail.com",
    "timestamp": "2025-02-07 00:31:40",
    "results": [
      "Invite Friends\nNot seeing your friends here? Send them an invite to join Skype!"
    ]
  },
  {
    "search_term": "Raghavendra.Manchikanti@nuance.com",
    "timestamp": "2025-02-07 00:31:47",
    "results": [
      "Invite Friends\nNot seeing your friends here? Send them an invite to join Skype!"
    ]
  },
  {
    "search_term": "sanatdatta23@gmail.com",
    "timestamp": "2025-02-07 00:31:55",
    "results": [
      "Invite Friends\nNot seeing your friends here? Send them an invite to join Skype!"
    ]
  },
  {
    "search_term": "etaxtion67@gmail.com",
    "timestamp": "2025-02-07 00:32:02",
    "results": [
      "Invite Friends\nNot seeing your friends here? Send them an invite to join Skype!"
    ]
  },
  {
    "search_term": "caansaha.asso@gmail.com",
    "timestamp": "2025-02-07 00:32:09",
    "results": [
      "Invite Friends\nNot seeing your friends here? Send them an invite to join Skype!"
    ]
  },
  {
    "search_term": "accounts@hardikdyechem.com",
    "timestamp": "2025-02-07 00:32:16",
    "results": [
      "Invite Friends\nNot seeing your friends here? Send them an invite to join Skype!"
    ]
  },
  {
    "search_term": "sushant@3003bc.com",
    "timestamp": "2025-02-07 00:32:23",
    "results": [
      "Invite Friends\nNot seeing your friends here? Send them an invite to join Skype!"
    ]
  },
  {
    "search_term": "rathtalaservicestation@gmail.com",
    "timestamp": "2025-02-07 00:32:31",
    "results": [
      "Invite Friends\nNot seeing your friends here? Send them an invite to join Skype!"
    ]
  },
  {
    "search_term": "debasish.sarkar@atclogistics.in",
    "timestamp": "2025-02-07 00:32:38",
    "results": [
      "Invite Friends\nNot seeing your friends here? Send them an invite to join Skype!"
    ]
  },
  {
    "search_term": "neeljanai7@gmail.com",
    "timestamp": "2025-02-07 00:32:45",
    "results": [
      "Invite Friends\nNot seeing your friends here? Send them an invite to join Skype!"
    ]
  },
  {
    "search_term": "halimagrofood@gmail.com",
    "timestamp": "2025-02-07 00:32:52",
    "results": [
      "Invite Friends\nNot seeing your friends here? Send them an invite to join Skype!"
    ]
  },
  {
    "search_term": "prsh_gpt@yahoo.co.in",
    "timestamp": "2025-02-07 00:32:59",
    "results": [
      "Invite Friends\nNot seeing your friends here? Send them an invite to join Skype!"
    ]
  },
  {
    "search_term": "debabratapaul45@gmail.com",
    "timestamp": "2025-02-07 00:33:07",
    "results": [
      "Invite Friends\nNot seeing your friends here? Send them an invite to join Skype!"
    ]
  },
  {
    "search_term": "incfrmbp2@gmail.com",
    "timestamp": "2025-02-07 00:33:14",
    "results": [
      "Invite Friends\nNot seeing your friends here? Send them an invite to join Skype!"
    ]
  },
  {
    "search_term": "tscs41@gmail.com",
    "timestamp": "2025-02-07 00:33:21",
    "results": [
      "Invite Friends\nNot seeing your friends here? Send them an invite to join Skype!"
    ]
  },
  {
    "search_term": "ssaha@aol.in",
    "timestamp": "2025-02-07 00:33:28",
    "results": [
      "Invite Friends\nNot seeing your friends here? Send them an invite to join Skype!"
    ]
  }
]